pyCATHY/__init__.py
pyCATHY/cathy_tools.py
pyCATHY/cathy_utils.py
pyCATHY/meshtools.py
pyCATHY/petro.py
pyCATHY/sensitivity.py
pyCATHY/DA/__init__.py
pyCATHY/DA/cathy_DA.py
pyCATHY/DA/enkf.py
pyCATHY/DA/localisation.py
pyCATHY/DA/mapper.py
pyCATHY/DA/observations.py
pyCATHY/DA/performance.py
pyCATHY/DA/perturbate.py
pyCATHY/DA/pf.py
pyCATHY/ERT/__init__.py
pyCATHY/ERT/petro_Archie.py
pyCATHY/ERT/simulate_ERT.py
pyCATHY/importers/__init__.py
pyCATHY/importers/cathy_inputs.py
pyCATHY/importers/cathy_outputs.py
pyCATHY/importers/cathy_plant.py
pyCATHY/importers/sensors_measures.py
pyCATHY/plotters/__init__.py
pyCATHY/plotters/cathyDA_plots.py
pyCATHY/plotters/cathy_plots.py
pyCATHY/tests/__init__.py
pyCATHY/tests/test_DA_ERT_Tensio_SWC.py
pyCATHY/tests/test_DA_Feddes_ERT.py
pyCATHY/tests/test_DA_Noble.py
pyCATHY/tests/test_hydro_surfsurbsurface.py
pyCATHY/tests/test_mapping.py
pycathy_wrapper-0.1.4.dist-info/licenses/AUTHORS.md
pycathy_wrapper-0.1.4.dist-info/licenses/LICENSE
pycathy_wrapper-0.1.4.dist-info/METADATA
pycathy_wrapper-0.1.4.dist-info/WHEEL
pycathy_wrapper-0.1.4.dist-info/top_level.txt
pycathy_wrapper-0.1.4.dist-info/zip-safe
pycathy_wrapper-0.1.4.dist-info/RECORD
