Metadata-Version: 2.4
Name: pycathy-wrapper
Version: 0.1.4
Summary: pyCATHY is a Python package to create, run, and post-process CATHY forward and inverse models.
Home-page: https://github.com/BenjMy/pycathy_wrapper
Author: B.Mary
Author-email: benjamin.mary@ica.csic.es
Project-URL: Bug Tracker, https://github.com/BenjMy/pycathy_wrapper/issues
Keywords: hydrogeophysic,Data Assimilation,hydrology
Classifier: Programming Language :: Python :: 3
Classifier: Development Status :: 5 - Production/Stable
Classifier: Intended Audience :: Science/Research
Classifier: Intended Audience :: Developers
Classifier: Intended Audience :: Education
Classifier: License :: OSI Approved :: BSD License
Classifier: Natural Language :: English
Classifier: Operating System :: OS Independent
Classifier: Topic :: Scientific/Engineering
Classifier: Topic :: Software Development :: Libraries
Classifier: Programming Language :: Python :: 3 :: Only
Classifier: Programming Language :: Python :: 3.7
Classifier: Programming Language :: Python :: 3.8
Requires-Python: >=3.7
License-File: LICENSE
License-File: AUTHORS.md
Requires-Dist: numpy
Requires-Dist: pandas
Requires-Dist: scipy
Requires-Dist: pyvista
Requires-Dist: SALib
Requires-Dist: GitPython
Requires-Dist: soiltexture
Requires-Dist: pyvistaqt
Requires-Dist: itkwidgets
Requires-Dist: rosetta-soil
Requires-Dist: rich
Requires-Dist: natsort
Requires-Dist: ipywidgets
Requires-Dist: smmap
Requires-Dist: shapely
Requires-Dist: imageio
Requires-Dist: nltk
Requires-Dist: geopandas
Requires-Dist: rioxarray
Requires-Dist: pyyaml
Dynamic: license-file
